{
  "schema_name": "DoclingDocument",
  "version": "1.7.0",
  "name": "Desaparece joven en Santiago; lo encuentran muerto en León",
  "origin": {
    "mimetype": "application/pdf",
    "binary_hash": 17344943471536749759,
    "filename": "Desaparece joven en Santiago; lo encuentran muerto en León.pdf"
  },
  "furniture": {
    "self_ref": "#/furniture",
    "children": [],
    "content_layer": "furniture",
    "name": "_root_",
    "label": "unspecified"
  },
  "body": {
    "self_ref": "#/body",
    "children": [
      {
        "$ref": "#/texts/0"
      }
    ],
    "content_layer": "body",
    "name": "_root_",
    "label": "unspecified"
  },
  "groups": [],
  "texts": [
    {
      "self_ref": "#/texts/0",
      "parent": {
        "$ref": "#/body"
      },
      "children": [],
      "content_layer": "body",
      "label": "text",
      "prov": [
        {
          "page_no": 1,
          "bbox": {
            "l": 30.273,
            "t": 706.0530075,
            "r": 632.273,
            "b": 6.934007500000007,
            "coord_origin": "BOTTOMLEFT"
          },
          "charspan": [
            0,
            5841
          ]
        },
        {
          "page_no": 2,
          "bbox": {
            "l": 30.273,
            "t": 706.3965875,
            "r": 620.233,
            "b": 635.2025874999999,
            "coord_origin": "BOTTOMLEFT"
          },
          "charspan": [
            5842,
            6370
          ]
        }
      ],
      "orig": "Desaparece joven en Santiago; lo encuentran muerto en León - vLex México VINCENT AI Productos Cobertura Integraciones Entrar Date de alta Inicio Noticias Norte - Monterrey 5 de Marzo de 2016 Desaparece joven en Santiago; lo encuentran muerto en León Document Citado por Relacionados Autor Mario Alberto Álvarez El 20 de febrero Aldo Misael Gutiérrez Treviño salió de su casa en San Nicolás, para dirigirse a una reunión de ex alumnos de FIME, en Santiago, pero ya no regresó. Ante la desaparición, su familia presentó una denuncia y por medio de redes sociales también lo buscaron. Este miércoles su familia recibió la trágica noticia de que el joven fue encontrado muerto de un balazo, en una habitación de un hotel de León, Guanajuato. Aunque las autoridades de ese Estado tomaron su muerte como un suicidio, la duda persiste. No se reveló el contenido del supuesto recado póstumo que encontraron en la... Para continuar leyendo Comienza Gratis Accede a todo el contenido con una prueba gratuita de 7 días Transforma tu investigación jurídica con vLex Accede a resúmenes de sentencias generados por IA, que destacan al instante los aspectos jurídicos clave. Realiza búsquedas avanzadas con opciones precisas de filtrado y ordenamiento. Consulta contenido jurídico completo de más de 100 jurisdicciones, incluyendo una amplia colección de libros y revistas a texto completo. Disfruta de funcionalidades exclusivas como comparador de versiones de una ley, notas de vigencia, análisis de citas, y mucho más. Con la confianza de más de 2 millones de profesionales, incluidas las firmas más importantes del mundo. Comienza Gratis Accede a todo el contenido con una prueba gratuita de 7 días Transforma tu investigación jurídica con vLex Accede a resúmenes de sentencias generados por IA, que destacan al instante los aspectos jurídicos clave. Realiza búsquedas avanzadas con opciones precisas de filtrado y ordenamiento. Consulta contenido jurídico completo de más de 100 jurisdicciones, incluyendo una amplia colección de libros y revistas a texto completo. Disfruta de funcionalidades exclusivas como comparador de versiones de una ley, notas de vigencia, análisis de citas, y mucho más. Con la confianza de más de 2 millones de profesionales, incluidas las firmas más importantes del mundo. Comienza Gratis Accede a todo el contenido con una prueba gratuita de 7 días Transforma tu investigación jurídica con vLex Accede a resúmenes de sentencias generados por IA, que destacan al instante los aspectos jurídicos clave. Realiza búsquedas avanzadas con opciones precisas de filtrado y ordenamiento. Consulta contenido jurídico completo de más de 100 jurisdicciones, incluyendo una amplia colección de libros y revistas a texto completo. Disfruta de funcionalidades exclusivas como comparador de versiones de una ley, notas de vigencia, análisis de citas, y mucho más. Con la confianza de más de 2 millones de profesionales, incluidas las firmas más importantes del mundo. Comienza Gratis Accede a todo el contenido con una prueba gratuita de 7 días Transforma tu investigación jurídica con vLex Accede a resúmenes de sentencias generados por IA, que destacan al instante los aspectos jurídicos clave. Realiza búsquedas avanzadas con opciones precisas de filtrado y ordenamiento. Consulta contenido jurídico completo de más de 100 jurisdicciones, incluyendo una amplia colección de libros y revistas a texto completo. Disfruta de funcionalidades exclusivas como comparador de versiones de una ley, notas de vigencia, análisis de citas, y mucho más. Con la confianza de más de 2 millones de profesionales, incluidas las firmas más importantes del mundo. Comienza Gratis Accede a todo el contenido con una prueba gratuita de 7 días Transforma tu investigación jurídica con vLex Accede a resúmenes de sentencias generados por IA, que destacan al instante los aspectos jurídicos clave. Realiza búsquedas avanzadas con opciones precisas de filtrado y ordenamiento. Consulta contenido jurídico completo de más de 100 jurisdicciones, incluyendo una amplia colección de libros y revistas a texto completo. Disfruta de funcionalidades exclusivas como comparador de versiones de una ley, notas de vigencia, análisis de citas, y mucho más. Con la confianza de más de 2 millones de profesionales, incluidas las firmas más importantes del mundo. Comienza Gratis Accede a todo el contenido con una prueba gratuita de 7 días Transforma tu investigación jurídica con vLex Accede a resúmenes de sentencias generados por IA, que destacan al instante los aspectos jurídicos clave. Realiza búsquedas avanzadas con opciones precisas de filtrado y ordenamiento. Consulta contenido jurídico completo de más de 100 jurisdicciones, incluyendo una amplia colección de libros y revistas a texto completo. Disfruta de funcionalidades exclusivas como comparador de versiones de una ley, notas de vigencia, análisis de citas, y mucho más. Con la confianza de más de 2 millones de profesionales, incluidas las firmas más importantes del mundo. Comienza Gratis Accede a todo el contenido con una prueba gratuita de 7 días Transforma tu investigación jurídica con vLex Accede a resúmenes de sentencias generados por IA, que destacan al instante los aspectos jurídicos clave. Realiza búsquedas avanzadas con opciones precisas de filtrado y ordenamiento. Consulta contenido jurídico completo de más de 100 jurisdicciones, incluyendo una amplia colección de libros y revistas a texto completo. Disfruta de funcionalidades exclusivas como comparador de versiones de una ley, notas de vigencia, análisis de citas, y mucho más. Con la confianza de más de 2 millones de profesionales, incluidas las firmas más importantes del mundo. Comienza Gratis × 7 días de acceso ilimitado 7 días de acceso ilimitado Búsquedas relacionadas: abandono de mercancias en aduanas Apelación en materia civil accidente de trabajo en trayecto codigo civil vigente en el estado de nuevo leon divorcio administrativo en nuevo leon pandillerismo en nuevo leon detenidos en el desierto de los leones mercado de trabajo para jovenes en mexico +52 (55) 416 971 36 Legislación Modelos y Formularios Diarios Oficiales Jurisprudencia Proyectos Normativos Prácticos vLex Doctrina Administrativa Noticias Tags Libros y Revistas Normatividad Índice de fuentes Descubre vLex Mobile Condiciones de uso ©2025 vLex.com Todos los derechos reservados",
      "text": "Desaparece joven en Santiago; lo encuentran muerto en León - vLex México VINCENT AI Productos Cobertura Integraciones Entrar Date de alta Inicio Noticias Norte - Monterrey 5 de Marzo de 2016 Desaparece joven en Santiago; lo encuentran muerto en León Document Citado por Relacionados Autor Mario Alberto Álvarez El 20 de febrero Aldo Misael Gutiérrez Treviño salió de su casa en San Nicolás, para dirigirse a una reunión de ex alumnos de FIME, en Santiago, pero ya no regresó. Ante la desaparición, su familia presentó una denuncia y por medio de redes sociales también lo buscaron. Este miércoles su familia recibió la trágica noticia de que el joven fue encontrado muerto de un balazo, en una habitación de un hotel de León, Guanajuato. Aunque las autoridades de ese Estado tomaron su muerte como un suicidio, la duda persiste. No se reveló el contenido del supuesto recado póstumo que encontraron en la... Para continuar leyendo Comienza Gratis Accede a todo el contenido con una prueba gratuita de 7 días Transforma tu investigación jurídica con vLex Accede a resúmenes de sentencias generados por IA, que destacan al instante los aspectos jurídicos clave. Realiza búsquedas avanzadas con opciones precisas de filtrado y ordenamiento. Consulta contenido jurídico completo de más de 100 jurisdicciones, incluyendo una amplia colección de libros y revistas a texto completo. Disfruta de funcionalidades exclusivas como comparador de versiones de una ley, notas de vigencia, análisis de citas, y mucho más. Con la confianza de más de 2 millones de profesionales, incluidas las firmas más importantes del mundo. Comienza Gratis Accede a todo el contenido con una prueba gratuita de 7 días Transforma tu investigación jurídica con vLex Accede a resúmenes de sentencias generados por IA, que destacan al instante los aspectos jurídicos clave. Realiza búsquedas avanzadas con opciones precisas de filtrado y ordenamiento. Consulta contenido jurídico completo de más de 100 jurisdicciones, incluyendo una amplia colección de libros y revistas a texto completo. Disfruta de funcionalidades exclusivas como comparador de versiones de una ley, notas de vigencia, análisis de citas, y mucho más. Con la confianza de más de 2 millones de profesionales, incluidas las firmas más importantes del mundo. Comienza Gratis Accede a todo el contenido con una prueba gratuita de 7 días Transforma tu investigación jurídica con vLex Accede a resúmenes de sentencias generados por IA, que destacan al instante los aspectos jurídicos clave. Realiza búsquedas avanzadas con opciones precisas de filtrado y ordenamiento. Consulta contenido jurídico completo de más de 100 jurisdicciones, incluyendo una amplia colección de libros y revistas a texto completo. Disfruta de funcionalidades exclusivas como comparador de versiones de una ley, notas de vigencia, análisis de citas, y mucho más. Con la confianza de más de 2 millones de profesionales, incluidas las firmas más importantes del mundo. Comienza Gratis Accede a todo el contenido con una prueba gratuita de 7 días Transforma tu investigación jurídica con vLex Accede a resúmenes de sentencias generados por IA, que destacan al instante los aspectos jurídicos clave. Realiza búsquedas avanzadas con opciones precisas de filtrado y ordenamiento. Consulta contenido jurídico completo de más de 100 jurisdicciones, incluyendo una amplia colección de libros y revistas a texto completo. Disfruta de funcionalidades exclusivas como comparador de versiones de una ley, notas de vigencia, análisis de citas, y mucho más. Con la confianza de más de 2 millones de profesionales, incluidas las firmas más importantes del mundo. Comienza Gratis Accede a todo el contenido con una prueba gratuita de 7 días Transforma tu investigación jurídica con vLex Accede a resúmenes de sentencias generados por IA, que destacan al instante los aspectos jurídicos clave. Realiza búsquedas avanzadas con opciones precisas de filtrado y ordenamiento. Consulta contenido jurídico completo de más de 100 jurisdicciones, incluyendo una amplia colección de libros y revistas a texto completo. Disfruta de funcionalidades exclusivas como comparador de versiones de una ley, notas de vigencia, análisis de citas, y mucho más. Con la confianza de más de 2 millones de profesionales, incluidas las firmas más importantes del mundo. Comienza Gratis Accede a todo el contenido con una prueba gratuita de 7 días Transforma tu investigación jurídica con vLex Accede a resúmenes de sentencias generados por IA, que destacan al instante los aspectos jurídicos clave. Realiza búsquedas avanzadas con opciones precisas de filtrado y ordenamiento. Consulta contenido jurídico completo de más de 100 jurisdicciones, incluyendo una amplia colección de libros y revistas a texto completo. Disfruta de funcionalidades exclusivas como comparador de versiones de una ley, notas de vigencia, análisis de citas, y mucho más. Con la confianza de más de 2 millones de profesionales, incluidas las firmas más importantes del mundo. Comienza Gratis Accede a todo el contenido con una prueba gratuita de 7 días Transforma tu investigación jurídica con vLex Accede a resúmenes de sentencias generados por IA, que destacan al instante los aspectos jurídicos clave. Realiza búsquedas avanzadas con opciones precisas de filtrado y ordenamiento. Consulta contenido jurídico completo de más de 100 jurisdicciones, incluyendo una amplia colección de libros y revistas a texto completo. Disfruta de funcionalidades exclusivas como comparador de versiones de una ley, notas de vigencia, análisis de citas, y mucho más. Con la confianza de más de 2 millones de profesionales, incluidas las firmas más importantes del mundo. Comienza Gratis × 7 días de acceso ilimitado 7 días de acceso ilimitado Búsquedas relacionadas: abandono de mercancias en aduanas Apelación en materia civil accidente de trabajo en trayecto codigo civil vigente en el estado de nuevo leon divorcio administrativo en nuevo leon pandillerismo en nuevo leon detenidos en el desierto de los leones mercado de trabajo para jovenes en mexico +52 (55) 416 971 36 Legislación Modelos y Formularios Diarios Oficiales Jurisprudencia Proyectos Normativos Prácticos vLex Doctrina Administrativa Noticias Tags Libros y Revistas Normatividad Índice de fuentes Descubre vLex Mobile Condiciones de uso ©2025 vLex.com Todos los derechos reservados"
    }
  ],
  "pictures": [],
  "tables": [],
  "key_value_items": [],
  "form_items": [],
  "pages": {
    "1": {
      "size": {
        "width": 639.0358276367188,
        "height": 744.3671875
      },
      "page_no": 1
    },
    "2": {
      "size": {
        "width": 627.0045776367188,
        "height": 662.49365234375
      },
      "page_no": 2
    }
  }
}